alibabacloud_milvus20231012/__init__.py
alibabacloud_milvus20231012/client.py
alibabacloud_milvus20231012/models/__init__.py
alibabacloud_milvus20231012/models/_change_resource_group_request.py
alibabacloud_milvus20231012/models/_change_resource_group_response.py
alibabacloud_milvus20231012/models/_change_resource_group_response_body.py
alibabacloud_milvus20231012/models/_create_default_role_response.py
alibabacloud_milvus20231012/models/_create_default_role_response_body.py
alibabacloud_milvus20231012/models/_create_instance_request.py
alibabacloud_milvus20231012/models/_create_instance_response.py
alibabacloud_milvus20231012/models/_create_instance_response_body.py
alibabacloud_milvus20231012/models/_dbversion_detail.py
alibabacloud_milvus20231012/models/_delete_instance_request.py
alibabacloud_milvus20231012/models/_delete_instance_response.py
alibabacloud_milvus20231012/models/_delete_instance_response_body.py
alibabacloud_milvus20231012/models/_describe_access_control_list_request.py
alibabacloud_milvus20231012/models/_describe_access_control_list_response.py
alibabacloud_milvus20231012/models/_describe_access_control_list_response_body.py
alibabacloud_milvus20231012/models/_describe_instance_configs_request.py
alibabacloud_milvus20231012/models/_describe_instance_configs_response.py
alibabacloud_milvus20231012/models/_describe_instance_configs_response_body.py
alibabacloud_milvus20231012/models/_get_instance_detail_request.py
alibabacloud_milvus20231012/models/_get_instance_detail_response.py
alibabacloud_milvus20231012/models/_get_instance_detail_response_body.py
alibabacloud_milvus20231012/models/_get_instance_request.py
alibabacloud_milvus20231012/models/_get_instance_response.py
alibabacloud_milvus20231012/models/_get_instance_response_body.py
alibabacloud_milvus20231012/models/_instance_detail.py
alibabacloud_milvus20231012/models/_list_instances_request.py
alibabacloud_milvus20231012/models/_list_instances_response.py
alibabacloud_milvus20231012-1.2.1.dist-info/LICENSE
alibabacloud_milvus20231012-1.2.1.dist-info/METADATA
alibabacloud_milvus20231012-1.2.1.dist-info/WHEEL
alibabacloud_milvus20231012-1.2.1.dist-info/top_level.txt
alibabacloud_milvus20231012-1.2.1.dist-info/RECORD
